sscompresshello/__init__.py
sscompresshello/sshello.py
sscompresshello_tutut-0.0.1.dist-info/licenses/LICENSE
sscompresshello_tutut-0.0.1.dist-info/METADATA
sscompresshello_tutut-0.0.1.dist-info/WHEEL
sscompresshello_tutut-0.0.1.dist-info/top_level.txt
sscompresshello_tutut-0.0.1.dist-info/RECORD
