Metadata-Version: 2.4
Name: sscompresshello-TuTuT
Version: 0.0.1
Summary: A simple hello-world packabg for testing PyPI upload.
Author-email: TuTuT <323949101@qq.com>
License: MIT
License-File: LICENSE
Dynamic: license-file
